LICENSE
autotyper/__init__.py
autotyper-3.0.2.dist-info/entry_points.txt
autotyper-3.0.2.dist-info/LICENSE
autotyper-3.0.2.dist-info/WHEEL
autotyper-3.0.2.dist-info/METADATA
autotyper-3.0.2.dist-info/RECORD
