Metadata-Version: 2.1
Name: autotyper
Version: 3.0.2
Summary: Paste the contents of the clipboard or a file to the cursor after a specified delay
Home-page: https://github.com/junaidrahim/autotyper
License: MIT
Keywords: autotyper,copy-paste
Author: Junaid Rahim
Author-email: junaidrahim8d@gmail.com
Requires-Python: >=3.8,<4.0
Classifier: License :: OSI Approved :: MIT License
Classifier: Programming Language :: Python :: 3
Classifier: Programming Language :: Python :: 3.8
Classifier: Programming Language :: Python :: 3.9
Requires-Dist: PyAutoGUI (>=0.9.52,<0.10.0)
Requires-Dist: pyperclip (>=1.8.1,<2.0.0)
Project-URL: Repository, https://github.com/junaidrahim/autotyper
